Metadata-Version: 2.1
Name: JakaModbusCommunication
Version: 4.0.8
Summary: A Modbus helper library for Jaka communication.
Home-page: https://github.com/cacher300/JakaModbusCom
Author: Lucas Pijl
Author-email: lapijl@uwaterloo.ca
Classifier: Programming Language :: Python :: 3.12
Classifier: License :: OSI Approved :: MIT License
Classifier: Operating System :: OS Independent
Requires-Python: >=3.7
Requires-Dist: pymodbus>=3.8.0
